kiss_icp-1.2.3.dist-info/WHEEL
kiss_icp-1.2.3.dist-info/RECORD
kiss_icp-1.2.3.dist-info/entry_points.txt
kiss_icp-1.2.3.dist-info/METADATA
kiss_icp-1.2.3.dist-info/licenses/LICENSE
kiss_icp/registration.py
kiss_icp/metrics.py
kiss_icp/preprocess.py
kiss_icp/mapping.py
kiss_icp/threshold.py
kiss_icp/voxelization.py
kiss_icp/__init__.py
kiss_icp/pipeline.py
kiss_icp/kiss_icp.py
kiss_icp/config/config.py
kiss_icp/config/__init__.py
kiss_icp/config/parser.py
kiss_icp/tools/pipeline_results.py
kiss_icp/tools/point_cloud2.py
kiss_icp/tools/cmd.py
kiss_icp/tools/progress_bar.py
kiss_icp/tools/__init__.py
kiss_icp/tools/visualizer.py
kiss_icp/datasets/kitti.py
kiss_icp/datasets/ouster.py
kiss_icp/datasets/tum.py
kiss_icp/datasets/helipr.py
kiss_icp/datasets/generic.py
kiss_icp/datasets/rosbag.py
kiss_icp/datasets/ncd.py
kiss_icp/datasets/mcap.py
kiss_icp/datasets/kitti_raw.py
kiss_icp/datasets/mulran.py
kiss_icp/datasets/nclt.py
kiss_icp/datasets/nuscenes.py
kiss_icp/datasets/__init__.py
kiss_icp/datasets/apollo.py
kiss_icp/datasets/boreas.py
kiss_icp/pybind/kiss_icp_pybind.cpython-311-x86_64-linux-gnu.so
