Metadata-Version: 2.2
Name: kiss-icp
Version: 1.2.3
Summary: Simple yet effective 3D LiDAR-Odometry registration pipeline
Keywords: LiDAR,Localization,Odometry,SLAM
Author-Email: Ignacio Vizzo <ignaciovizzo@gmail.com>, Tiziano Guadagnino <frevo93@gmail.com>, Benedikt Mersch <benedikt.mersch@gmail.com>
Classifier: Intended Audience :: Developers
Classifier: Intended Audience :: Education
Classifier: Intended Audience :: Other Audience
Classifier: Intended Audience :: Science/Research
Classifier: License :: OSI Approved :: MIT License
Classifier: Operating System :: MacOS
Classifier: Operating System :: Microsoft :: Windows
Classifier: Operating System :: Unix
Classifier: Programming Language :: C++
Classifier: Programming Language :: Python :: 3
Classifier: Programming Language :: Python :: 3.8
Classifier: Programming Language :: Python :: 3.9
Classifier: Programming Language :: Python :: 3.10
Classifier: Programming Language :: Python :: 3.11
Classifier: Programming Language :: Python :: 3.12
Classifier: Programming Language :: Python :: 3.13
Project-URL: Homepage, https://github.com/PRBonn/kiss-icp
Requires-Python: >=3.8
Requires-Dist: natsort
Requires-Dist: numpy
Requires-Dist: pydantic>=2
Requires-Dist: pydantic-settings
Requires-Dist: pyquaternion
Requires-Dist: rich
Requires-Dist: tqdm
Requires-Dist: typer[all]>=0.6.0
Provides-Extra: all
Requires-Dist: open3d>=0.16; extra == "all"
Requires-Dist: polyscope>=2.2.1; extra == "all"
Requires-Dist: ouster-sdk>=0.11; extra == "all"
Requires-Dist: pyntcloud; extra == "all"
Requires-Dist: PyYAML; extra == "all"
Requires-Dist: trimesh; extra == "all"
Provides-Extra: test
Requires-Dist: pytest; extra == "test"
Provides-Extra: visualizer
Requires-Dist: open3d>=0.13; extra == "visualizer"
